sciencebeam_utils/__init__.py
sciencebeam_utils/beam_utils/__init__.py
sciencebeam_utils/beam_utils/csv.py
sciencebeam_utils/beam_utils/files.py
sciencebeam_utils/beam_utils/io.py
sciencebeam_utils/beam_utils/main.py
sciencebeam_utils/beam_utils/testing.py
sciencebeam_utils/beam_utils/utils.py
sciencebeam_utils/tools/__init__.py
sciencebeam_utils/tools/check_file_list.py
sciencebeam_utils/tools/find_file_pairs.py
sciencebeam_utils/tools/get_output_files.py
sciencebeam_utils/tools/split_csv_dataset.py
sciencebeam_utils/tools/tool_utils.py
sciencebeam_utils/utils/__init__.py
sciencebeam_utils/utils/collection.py
sciencebeam_utils/utils/compat.py
sciencebeam_utils/utils/csv.py
sciencebeam_utils/utils/exceptions.py
sciencebeam_utils/utils/file_list.py
sciencebeam_utils/utils/file_pairs.py
sciencebeam_utils/utils/file_path.py
sciencebeam_utils/utils/num.py
sciencebeam_utils/utils/progress_logger.py
sciencebeam_utils/utils/stopwatch.py
sciencebeam_utils/utils/string.py
sciencebeam_utils/utils/tqdm.py
sciencebeam_utils/utils/xml.py
sciencebeam_utils/utils/zip.py
tests/__init__.py
tests/conftest.py
tests/beam_utils/__init__.py
tests/beam_utils/csv_test.py
tests/beam_utils/files_test.py
tests/beam_utils/main_test.py
tests/beam_utils/utils_test.py
tests/tools/__init__.py
tests/tools/check_file_list_test.py
tests/tools/find_file_pairs_test.py
tests/tools/get_output_files_test.py
tests/tools/split_csv_dataset_test.py
tests/utils/__init__.py
tests/utils/compat_test.py
tests/utils/exceptions_test.py
tests/utils/file_list_test.py
tests/utils/file_pairs_test.py
tests/utils/file_path_test.py
tests/utils/progress_logger_test.py
tests/utils/string_test.py
tests/utils/tqdm_test.py
tests/utils/xml_test.py
sciencebeam_utils-0.1.5.dist-info/METADATA
sciencebeam_utils-0.1.5.dist-info/WHEEL
sciencebeam_utils-0.1.5.dist-info/top_level.txt
sciencebeam_utils-0.1.5.dist-info/RECORD
