Metadata-Version: 2.1
Name: sciencebeam-utils
Version: 0.1.5
Summary: ScienceBeam Utils
Home-page: https://github.com/elifesciences/sciencebeam-utils
Author: eLife Sciences Publications, Ltd
License: UNKNOWN
Platform: UNKNOWN
Requires-Dist: backports.tempfile (>=1.0)
Requires-Dist: backports.csv (>=1.0)
Requires-Dist: lxml (>=4.2.0)
Requires-Dist: numpy (>=1.14.2)
Requires-Dist: six (>=1.11.0)
Requires-Dist: tqdm (>=4.0.0)
